MANIFEST.in
README.rst
requirements-test.txt
requirements.txt
setup.py
certificator/__init__.py
certificator/__main__.py
certificator/certificator.py
certificator/config.py
certificator.egg-info/PKG-INFO
certificator.egg-info/SOURCES.txt
certificator.egg-info/dependency_links.txt
certificator.egg-info/entry_points.txt
certificator.egg-info/requires.txt
certificator.egg-info/top_level.txt
certificator/meetup/__init__.py
certificator/meetup/client.py
certificator/meetup/models.py
certificator/templates/styles.css
certificator/templates/template.html