Metadata-Version: 1.1
Name: certificator
Version: 0.0.5
Summary: Certificate Generator Tool and Library
Home-page: https://github.com/lamenezes/certificator
Author: Luiz Menezes
Author-email: luiz.menezesf@gmail.com
License: UNKNOWN
Platform: UNKNOWN
Classifier: Development Status :: 3 - Alpha
Classifier: Environment :: Console
Classifier: Intended Audience :: Developers
Classifier: Programming Language :: Python :: 3
Classifier: Programming Language :: Python :: 3.5
